shadcn_agent/__init__.py
shadcn_agent/cli.py
shadcn_agent/playground.py
shadcn_agent-0.2.0.dist-info/METADATA
shadcn_agent-0.2.0.dist-info/WHEEL
shadcn_agent-0.2.0.dist-info/entry_points.txt
shadcn_agent-0.2.0.dist-info/licenses/LICENSE
shadcn_agent-0.2.0.dist-info/RECORD
