Metadata-Version: 2.4
Name: shadcn-agent
Version: 0.2.0
Summary: A Shadcn-style CLI for building composable AI agents with LangGraph. Fetch component templates directly from GitHub.
Project-URL: Homepage, https://github.com/Aryan-Bagale/shadcn-agents
Project-URL: Repository, https://github.com/Aryan-Bagale/shadcn-agents
Project-URL: Issues, https://github.com/Aryan-Bagale/shadcn-agents/issues
Project-URL: Documentation, https://github.com/Aryan-Bagale/shadcn-agents#readme
Project-URL: Changelog, https://github.com/Aryan-Bagale/shadcn-agents/releases
Author-email: Aryan Bagale <aryanbagale22@gmail.com>
License-Expression: MIT
License-File: LICENSE
Keywords: agents,ai,automation,cli,langgraph,workflow
Classifier: Development Status :: 4 - Beta
Classifier: Intended Audience :: Developers
Classifier: License :: OSI Approved :: MIT License
Classifier: Operating System :: OS Independent
Classifier: Programming Language :: Python :: 3
Classifier: Programming Language :: Python :: 3.8
Classifier: Programming Language :: Python :: 3.9
Classifier: Programming Language :: Python :: 3.10
Classifier: Programming Language :: Python :: 3.11
Classifier: Programming Language :: Python :: 3.12
Classifier: Topic :: Scientific/Engineering :: Artificial Intelligence
Classifier: Topic :: Software Development :: Code Generators
Classifier: Topic :: Software Development :: Libraries :: Python Modules
Classifier: Topic :: System :: Systems Administration
Requires-Python: >=3.8
Requires-Dist: beautifulsoup4>=4.9.0
Requires-Dist: deep-translator>=1.9.0
Requires-Dist: langgraph>=0.0.1; python_version >= '3.9'
Requires-Dist: python-dotenv>=0.19.0
Requires-Dist: requests>=2.25.0
Provides-Extra: all
Requires-Dist: black>=21.0; extra == 'all'
Requires-Dist: flake8>=3.8; extra == 'all'
Requires-Dist: mypy>=0.900; extra == 'all'
Requires-Dist: pre-commit>=2.0; extra == 'all'
Requires-Dist: pytest-cov>=2.0; extra == 'all'
Requires-Dist: pytest>=6.0; extra == 'all'
Requires-Dist: streamlit>=1.20.0; extra == 'all'
Provides-Extra: dev
Requires-Dist: black>=21.0; extra == 'dev'
Requires-Dist: flake8>=3.8; extra == 'dev'
Requires-Dist: mypy>=0.900; extra == 'dev'
Requires-Dist: pre-commit>=2.0; extra == 'dev'
Requires-Dist: pytest-cov>=2.0; extra == 'dev'
Requires-Dist: pytest>=6.0; extra == 'dev'
Provides-Extra: playground
Requires-Dist: streamlit>=1.20.0; extra == 'playground'
